{"geradoEm":"2026-06-24T19:28:00.546Z","bundlePath":"/data/bundles/lexus/nx-350h-4x4-dynamic-2-5-16v-aut-hib-2024-057054-0.json","identity":{"vehicleId":"lexus-nx-350h-4x4-dynamic-2-5-16v-aut-hib-2024-hibrido","marca":"Lexus","marcaSlug":"lexus","modelo":"NX-350h 4x4 Dynamic 2.5 16V Aut. (Híb.)","ano":2024,"anoModelo":2024,"displayYear":{"kind":"year","year":2024,"label":"2024","shortLabel":"2024"},"combustivel":"Híbrido","tipo":"carros","displayName":"Lexus Nx-350H 4X4 Dynamic 2.5 16V Aut. (híb.)","pageSlug":"nx-350h-4x4-dynamic-2-5-16v-aut-hib-2024-057054-0"},"fipe":{"fipeCodigo":"057054-0","valorAtual":317975,"mesReferencia":"Jun/26","historico":[{"referencia":"Fev/24","valor":357618,"data":"2024-02-01"},{"referencia":"Mar/24","valor":356366,"data":"2024-03-01"},{"referencia":"Abr/24","valor":356294,"data":"2024-04-01"},{"referencia":"Mai/24","valor":357149,"data":"2024-05-01"},{"referencia":"Jun/24","valor":355898,"data":"2024-06-01"},{"referencia":"Jul/24","valor":354759,"data":"2024-07-01"},{"referencia":"Ago/24","valor":353588,"data":"2024-08-01"},{"referencia":"Set/24","valor":341989,"data":"2024-09-01"},{"referencia":"Out/24","valor":341236,"data":"2024-10-01"},{"referencia":"Nov/24","valor":340417,"data":"2024-11-01"},{"referencia":"Dez/24","valor":339770,"data":"2024-12-01"},{"referencia":"Jan/25","valor":339124,"data":"2025-01-01"},{"referencia":"Fev/25","valor":338377,"data":"2025-02-01"},{"referencia":"Mar/25","valor":338173,"data":"2025-03-01"},{"referencia":"Abr/25","valor":337665,"data":"2025-04-01"},{"referencia":"Mai/25","valor":337361,"data":"2025-05-01"},{"referencia":"Jun/25","valor":336686,"data":"2025-06-01"},{"referencia":"Jul/25","valor":336349,"data":"2025-07-01"},{"referencia":"Ago/25","valor":335810,"data":"2025-08-01"},{"referencia":"Set/25","valor":335104,"data":"2025-09-01"},{"referencia":"Out/25","valor":334031,"data":"2025-10-01"},{"referencia":"Nov/25","valor":332360,"data":"2025-11-01"},{"referencia":"Dez/25","valor":330698,"data":"2025-12-01"},{"referencia":"Jan/26","valor":329044,"data":"2026-01-01"},{"referencia":"Fev/26","valor":328320,"data":"2026-02-01"},{"referencia":"Mar/26","valor":320149,"data":"2026-03-01"},{"referencia":"Abr/26","valor":319028,"data":"2026-04-01"},{"referencia":"Mai/26","valor":318581,"data":"2026-05-01"},{"referencia":"Jun/26","valor":317975,"data":"2026-06-01"}],"trend6m":-3.8473168873110817},"specs":{"potenciaCv":null,"torqueNm":null,"cilindradaCc":null,"cambio":"Automatico","pesoKg":null,"comprimentoMm":null,"larguraMm":null,"alturaMm":null,"portaMalasL":null,"tanqueL":null,"aceleracao0a100":null,"velocidadeMaxKmh":null,"fonte":"static-catalog"},"engine":null,"maintenance":null,"platform":null,"transmission":null,"generation":{"geracaoId":"nx-2","familia":"lexus|nx","catalogEntry":{"id":"nx-2","numero":2,"anoInicio":2015,"anoFim":2027,"label":"NX gen 2 (2015-2027)"}},"inmetro":{"consumoCidade":14.5,"consumoEstrada":12.7,"consumoCidadeEtanol":36.1,"consumoEstradaEtanol":29.6,"potenciaCv":null,"cilindradaCc":null,"classificacaoEnergetica":"A","fonte":"inmetro-pbev","matchKey":"lexus|nx","edicaoId":"pbev-mascara-pbev-2025-mar-11","anoReferencia":2026,"matchTier":"family_prefix","confidence":70,"matchedBy":"family:nx","metricProfile":"hibrido"},"safety":null,"recalls":null,"warranty":null,"provenance":{"valorFipe":{"value":317975,"source":"FIPE","origin":"Tabela FIPE (Jun/26)","confidence":100,"lastVerified":"2026-06-24"},"consumoCidade":{"value":14.5,"source":"INMETRO","origin":"PBEV (mascara pbev 2025 mar 11)","sourceYear":2026,"confidence":70,"sourceUrl":"https://www.gov.br/inmetro/pt-br/assuntos/regulamentacao/avaliacao-da-conformidade/programa-brasileiro-de-etiquetagem-veicular","lastVerified":"2026-06-24","matchedBy":"family:nx","estimated":true},"consumoEstrada":{"value":12.7,"source":"INMETRO","origin":"PBEV (mascara pbev 2025 mar 11)","sourceYear":2026,"confidence":70,"sourceUrl":"https://www.gov.br/inmetro/pt-br/assuntos/regulamentacao/avaliacao-da-conformidade/programa-brasileiro-de-etiquetagem-veicular","lastVerified":"2026-06-24","matchedBy":"family:nx","estimated":true},"classificacaoEnergetica":{"value":"A","source":"INMETRO","origin":"PBEV (mascara pbev 2025 mar 11)","sourceYear":2026,"confidence":70,"sourceUrl":"https://www.gov.br/inmetro/pt-br/assuntos/regulamentacao/avaliacao-da-conformidade/programa-brasileiro-de-etiquetagem-veicular","lastVerified":"2026-06-24","matchedBy":"family:nx","estimated":true},"cambio":{"value":"Automatico","source":"Catálogo estático","confidence":41,"lastVerified":"2026-06-24"}},"related":{"mesmaGeracao":[{"vehicleId":"lexus-nx-200t-f-sport-awd-2-0-16v-238cv-aut-2015-gasolina","fipeCodigo":"057039-7","displayName":"Lexus Nx-200T F-Sport AWD 2.0 16V 238CV Aut.","valorAtual":115302,"canonicalPath":"/fipe/lexus/nx-200t-f-sport-awd-2-0-16v-238cv-aut-2015-057039-7/","ano":2015,"marca":"Lexus","modelo":"NX-200t F-Sport AWD 2.0 16v 238cv Aut.","tipo":"carros","displayYear":{"kind":"year","year":2015,"label":"2015","shortLabel":"2015"}},{"vehicleId":"lexus-nx-200t-f-sport-awd-2-0-16v-238cv-aut-2016-gasolina","fipeCodigo":"057039-7","displayName":"Lexus Nx-200T F-Sport AWD 2.0 16V 238CV Aut.","valorAtual":120480,"canonicalPath":"/fipe/lexus/nx-200t-f-sport-awd-2-0-16v-238cv-aut-2016-057039-7/","ano":2016,"marca":"Lexus","modelo":"NX-200t F-Sport AWD 2.0 16v 238cv Aut.","tipo":"carros","displayYear":{"kind":"year","year":2016,"label":"2016","shortLabel":"2016"}},{"vehicleId":"lexus-nx-200t-f-sport-awd-2-0-16v-238cv-aut-2017-gasolina","fipeCodigo":"057039-7","displayName":"Lexus Nx-200T F-Sport AWD 2.0 16V 238CV Aut.","valorAtual":129591,"canonicalPath":"/fipe/lexus/nx-200t-f-sport-awd-2-0-16v-238cv-aut-2017-057039-7/","ano":2017,"marca":"Lexus","modelo":"NX-200t F-Sport AWD 2.0 16v 238cv Aut.","tipo":"carros","displayYear":{"kind":"year","year":2017,"label":"2017","shortLabel":"2017"}},{"vehicleId":"lexus-nx-200t-luxury-awd-2-0-16v-238cv-aut-2015-gasolina","fipeCodigo":"057038-9","displayName":"Lexus Nx-200T Luxury AWD 2.0 16V 238CV Aut.","valorAtual":103256,"canonicalPath":"/fipe/lexus/nx-200t-luxury-awd-2-0-16v-238cv-aut-2015-057038-9/","ano":2015,"marca":"Lexus","modelo":"NX-200t Luxury AWD 2.0 16V 238cv Aut.","tipo":"carros","displayYear":{"kind":"year","year":2015,"label":"2015","shortLabel":"2015"}},{"vehicleId":"lexus-nx-200t-luxury-awd-2-0-16v-238cv-aut-2016-gasolina","fipeCodigo":"057038-9","displayName":"Lexus Nx-200T Luxury AWD 2.0 16V 238CV Aut.","valorAtual":107900,"canonicalPath":"/fipe/lexus/nx-200t-luxury-awd-2-0-16v-238cv-aut-2016-057038-9/","ano":2016,"marca":"Lexus","modelo":"NX-200t Luxury AWD 2.0 16V 238cv Aut.","tipo":"carros","displayYear":{"kind":"year","year":2016,"label":"2016","shortLabel":"2016"}},{"vehicleId":"lexus-nx-200t-luxury-awd-2-0-16v-238cv-aut-2017-gasolina","fipeCodigo":"057038-9","displayName":"Lexus Nx-200T Luxury AWD 2.0 16V 238CV Aut.","valorAtual":127351,"canonicalPath":"/fipe/lexus/nx-200t-luxury-awd-2-0-16v-238cv-aut-2017-057038-9/","ano":2017,"marca":"Lexus","modelo":"NX-200t Luxury AWD 2.0 16V 238cv Aut.","tipo":"carros","displayYear":{"kind":"year","year":2017,"label":"2017","shortLabel":"2017"}}],"mesmaFamilia":[{"vehicleId":"lexus-nx-200t-f-sport-awd-2-0-16v-238cv-aut-2015-gasolina","fipeCodigo":"057039-7","displayName":"Lexus Nx-200T F-Sport AWD 2.0 16V 238CV Aut.","valorAtual":115302,"canonicalPath":"/fipe/lexus/nx-200t-f-sport-awd-2-0-16v-238cv-aut-2015-057039-7/","ano":2015,"marca":"Lexus","modelo":"NX-200t F-Sport AWD 2.0 16v 238cv Aut.","tipo":"carros","displayYear":{"kind":"year","year":2015,"label":"2015","shortLabel":"2015"}},{"vehicleId":"lexus-nx-200t-f-sport-awd-2-0-16v-238cv-aut-2016-gasolina","fipeCodigo":"057039-7","displayName":"Lexus Nx-200T F-Sport AWD 2.0 16V 238CV Aut.","valorAtual":120480,"canonicalPath":"/fipe/lexus/nx-200t-f-sport-awd-2-0-16v-238cv-aut-2016-057039-7/","ano":2016,"marca":"Lexus","modelo":"NX-200t F-Sport AWD 2.0 16v 238cv Aut.","tipo":"carros","displayYear":{"kind":"year","year":2016,"label":"2016","shortLabel":"2016"}},{"vehicleId":"lexus-nx-200t-f-sport-awd-2-0-16v-238cv-aut-2017-gasolina","fipeCodigo":"057039-7","displayName":"Lexus Nx-200T F-Sport AWD 2.0 16V 238CV Aut.","valorAtual":129591,"canonicalPath":"/fipe/lexus/nx-200t-f-sport-awd-2-0-16v-238cv-aut-2017-057039-7/","ano":2017,"marca":"Lexus","modelo":"NX-200t F-Sport AWD 2.0 16v 238cv Aut.","tipo":"carros","displayYear":{"kind":"year","year":2017,"label":"2017","shortLabel":"2017"}},{"vehicleId":"lexus-nx-200t-luxury-awd-2-0-16v-238cv-aut-2015-gasolina","fipeCodigo":"057038-9","displayName":"Lexus Nx-200T Luxury AWD 2.0 16V 238CV Aut.","valorAtual":103256,"canonicalPath":"/fipe/lexus/nx-200t-luxury-awd-2-0-16v-238cv-aut-2015-057038-9/","ano":2015,"marca":"Lexus","modelo":"NX-200t Luxury AWD 2.0 16V 238cv Aut.","tipo":"carros","displayYear":{"kind":"year","year":2015,"label":"2015","shortLabel":"2015"}},{"vehicleId":"lexus-nx-200t-luxury-awd-2-0-16v-238cv-aut-2016-gasolina","fipeCodigo":"057038-9","displayName":"Lexus Nx-200T Luxury AWD 2.0 16V 238CV Aut.","valorAtual":107900,"canonicalPath":"/fipe/lexus/nx-200t-luxury-awd-2-0-16v-238cv-aut-2016-057038-9/","ano":2016,"marca":"Lexus","modelo":"NX-200t Luxury AWD 2.0 16V 238cv Aut.","tipo":"carros","displayYear":{"kind":"year","year":2016,"label":"2016","shortLabel":"2016"}},{"vehicleId":"lexus-nx-200t-luxury-awd-2-0-16v-238cv-aut-2017-gasolina","fipeCodigo":"057038-9","displayName":"Lexus Nx-200T Luxury AWD 2.0 16V 238CV Aut.","valorAtual":127351,"canonicalPath":"/fipe/lexus/nx-200t-luxury-awd-2-0-16v-238cv-aut-2017-057038-9/","ano":2017,"marca":"Lexus","modelo":"NX-200t Luxury AWD 2.0 16V 238cv Aut.","tipo":"carros","displayYear":{"kind":"year","year":2017,"label":"2017","shortLabel":"2017"}}],"mesmaPlataforma":[],"mesmoMotor":[],"mesmaTransmissao":[],"mesmaFaixaPreco":[{"vehicleId":"am-gen-hummer-hard-top-6-5-4x4-diesel-tb-1998-diesel","fipeCodigo":"037001-0","displayName":"AM Gen Hummer Hard-Top 6.5 4X4 Diesel TB","valorAtual":324626,"canonicalPath":"/fipe/am-gen/hummer-hard-top-6-5-4x4-diesel-tb-1998-037001-0/","ano":1998,"marca":"AM Gen","modelo":"Hummer Hard-Top 6.5 4x4 Diesel TB","tipo":"carros","displayYear":{"kind":"year","year":1998,"label":"1998","shortLabel":"1998"}},{"vehicleId":"am-gen-hummer-hard-top-6-5-4x4-diesel-tb-1999-diesel","fipeCodigo":"037001-0","displayName":"AM Gen Hummer Hard-Top 6.5 4X4 Diesel TB","valorAtual":374894,"canonicalPath":"/fipe/am-gen/hummer-hard-top-6-5-4x4-diesel-tb-1999-037001-0/","ano":1999,"marca":"AM Gen","modelo":"Hummer Hard-Top 6.5 4x4 Diesel TB","tipo":"carros","displayYear":{"kind":"year","year":1999,"label":"1999","shortLabel":"1999"}},{"vehicleId":"am-gen-hummer-hard-top-6-5-4x4-diesel-tb-2000-diesel","fipeCodigo":"037001-0","displayName":"AM Gen Hummer Hard-Top 6.5 4X4 Diesel TB","valorAtual":416343,"canonicalPath":"/fipe/am-gen/hummer-hard-top-6-5-4x4-diesel-tb-2000-037001-0/","ano":2000,"marca":"AM Gen","modelo":"Hummer Hard-Top 6.5 4x4 Diesel TB","tipo":"carros","displayYear":{"kind":"year","year":2000,"label":"2000","shortLabel":"2000"}},{"vehicleId":"am-gen-hummer-open-top-6-5-4x4-diesel-tb-1998-diesel","fipeCodigo":"037002-9","displayName":"AM Gen Hummer Open-Top 6.5 4X4 Diesel TB","valorAtual":329573,"canonicalPath":"/fipe/am-gen/hummer-open-top-6-5-4x4-diesel-tb-1998-037002-9/","ano":1998,"marca":"AM Gen","modelo":"Hummer Open-Top 6.5 4x4 Diesel TB","tipo":"carros","displayYear":{"kind":"year","year":1998,"label":"1998","shortLabel":"1998"}},{"vehicleId":"am-gen-hummer-open-top-6-5-4x4-diesel-tb-1999-diesel","fipeCodigo":"037002-9","displayName":"AM Gen Hummer Open-Top 6.5 4X4 Diesel TB","valorAtual":381794,"canonicalPath":"/fipe/am-gen/hummer-open-top-6-5-4x4-diesel-tb-1999-037002-9/","ano":1999,"marca":"AM Gen","modelo":"Hummer Open-Top 6.5 4x4 Diesel TB","tipo":"carros","displayYear":{"kind":"year","year":1999,"label":"1999","shortLabel":"1999"}},{"vehicleId":"am-gen-hummer-open-top-6-5-4x4-diesel-tb-2000-diesel","fipeCodigo":"037002-9","displayName":"AM Gen Hummer Open-Top 6.5 4X4 Diesel TB","valorAtual":418764,"canonicalPath":"/fipe/am-gen/hummer-open-top-6-5-4x4-diesel-tb-2000-037002-9/","ano":2000,"marca":"AM Gen","modelo":"Hummer Open-Top 6.5 4x4 Diesel TB","tipo":"carros","displayYear":{"kind":"year","year":2000,"label":"2000","shortLabel":"2000"}}],"concorrentes":[{"vehicleId":"lexus-rx-450h-f-sport-awd-3-5-24v-v6-aut-hib-2022-hibrido","fipeCodigo":"057052-4","displayName":"Lexus Rx-450H F-Sport AWD 3.5 24V V6 Aut(híb.)","valorAtual":328261,"canonicalPath":"/fipe/lexus/rx-450h-f-sport-awd-3-5-24v-v6-aut-hib-2022-057052-4/","ano":2022,"marca":"Lexus","modelo":"RX-450h F-Sport AWD 3.5 24V V6 Aut(Híb.)","tipo":"carros","displayYear":{"kind":"year","year":2022,"label":"2022","shortLabel":"2022"}},{"vehicleId":"lexus-rx-450h-f-sport-awd-3-5-24v-v6-aut-hib-2021-hibrido","fipeCodigo":"057052-4","displayName":"Lexus Rx-450H F-Sport AWD 3.5 24V V6 Aut(híb.)","valorAtual":320254,"canonicalPath":"/fipe/lexus/rx-450h-f-sport-awd-3-5-24v-v6-aut-hib-2021-057052-4/","ano":2021,"marca":"Lexus","modelo":"RX-450h F-Sport AWD 3.5 24V V6 Aut(Híb.)","tipo":"carros","displayYear":{"kind":"year","year":2021,"label":"2021","shortLabel":"2021"}},{"vehicleId":"mitsubishi-pajero-sport-legend-2-4-4x4-diesel-aut-2024-diesel","fipeCodigo":"022204-6","displayName":"Mitsubishi Pajero Sport Legend 2.4 4X4 Diesel Aut.","valorAtual":318044,"canonicalPath":"/fipe/mitsubishi/pajero-sport-legend-2-4-4x4-diesel-aut-2024-022204-6/","ano":2024,"marca":"Mitsubishi","modelo":"Pajero Sport Legend 2.4 4x4 Diesel Aut.","tipo":"carros","displayYear":{"kind":"year","year":2024,"label":"2024","shortLabel":"2024"}},{"vehicleId":"bmw-ix-3-m-sport-aut-eletrico-2024-eletrico","fipeCodigo":"009297-5","displayName":"BMW Ix 3 M Sport Aut.(elétrico)","valorAtual":317548,"canonicalPath":"/fipe/bmw/ix-3-m-sport-aut-eletrico-2024-009297-5/","ano":2024,"marca":"BMW","modelo":"iX 3 M Sport Aut.(Elétrico)","tipo":"carros","displayYear":{"kind":"year","year":2024,"label":"2024","shortLabel":"2024"}},{"vehicleId":"bmw-330e-m-sport-2-0-turbo-aut-hibrido-2024-hibrido","fipeCodigo":"009266-5","displayName":"BMW 330E M Sport 2.0 Turbo Aut. (híbrido)","valorAtual":317068,"canonicalPath":"/fipe/bmw/330e-m-sport-2-0-turbo-aut-hibrido-2024-009266-5/","ano":2024,"marca":"BMW","modelo":"330e M Sport 2.0 Turbo Aut. (Híbrido)","tipo":"carros","displayYear":{"kind":"year","year":2024,"label":"2024","shortLabel":"2024"}},{"vehicleId":"land-rover-discovery-sp-se-dyn-2-0-p250-flex-aut-2024-flex","fipeCodigo":"033232-1","displayName":"Land Rover Discovery Sp. SE Dyn 2.0 P250 Flex Aut.","valorAtual":316529,"canonicalPath":"/fipe/land-rover/discovery-sp-se-dyn-2-0-p250-flex-aut-2024-033232-1/","ano":2024,"marca":"Land Rover","modelo":"Discovery Sp. SE Dyn 2.0 P250 Flex Aut.","tipo":"carros","displayYear":{"kind":"year","year":2024,"label":"2024","shortLabel":"2024"}},{"vehicleId":"toyota-corolla-gr-core-1-6-turbo-4x4-mec-2024-gasolina","fipeCodigo":"002212-8","displayName":"Toyota Corolla Gr Core 1.6 Turbo 4X4 Mec","valorAtual":320657,"canonicalPath":"/fipe/toyota/corolla-gr-core-1-6-turbo-4x4-mec-2024-002212-8/","ano":2024,"marca":"Toyota","modelo":"Corolla GR Core 1.6 Turbo 4x4 Mec","tipo":"carros","displayYear":{"kind":"year","year":2024,"label":"2024","shortLabel":"2024"}},{"vehicleId":"mitsubishi-pajero-sport-le-black-2-4-4x4-die-aut-2024-diesel","fipeCodigo":"022209-7","displayName":"Mitsubishi Pajero Sport LE.Black 2.4 4X4 (die) Aut.","valorAtual":320973,"canonicalPath":"/fipe/mitsubishi/pajero-sport-le-black-2-4-4x4-die-aut-2024-022209-7/","ano":2024,"marca":"Mitsubishi","modelo":"Pajero Sport Le.Black 2.4 4x4 (Die) Aut.","tipo":"carros","displayYear":{"kind":"year","year":2024,"label":"2024","shortLabel":"2024"}},{"vehicleId":"bmw-i4-e-drive-35-m-sport-eletrico-2024-eletrico","fipeCodigo":"009306-8","displayName":"BMW I4 e-Drive 35 M Sport (elétrico)","valorAtual":321471,"canonicalPath":"/fipe/bmw/i4-e-drive-35-m-sport-eletrico-2024-009306-8/","ano":2024,"marca":"BMW","modelo":"i4 e-Drive 35 M Sport (Elétrico)","tipo":"carros","displayYear":{"kind":"year","year":2024,"label":"2024","shortLabel":"2024"}},{"vehicleId":"mercedes-benz-eqb-350-eletrico-2024-eletrico","fipeCodigo":"021524-4","displayName":"Mercedes-Benz Eqb 350 (elétrico)","valorAtual":314266,"canonicalPath":"/fipe/mercedes-benz/eqb-350-eletrico-2024-021524-4/","ano":2024,"marca":"Mercedes-Benz","modelo":"EQB 350 (Elétrico)","tipo":"carros","displayYear":{"kind":"year","year":2024,"label":"2024","shortLabel":"2024"}},{"vehicleId":"audi-q5-s-line-black-2-0-tfsi-quat-s-tronic-2024-gasolina","fipeCodigo":"008270-8","displayName":"Audi Q5 S-Line Black 2.0 TFSI Quat. S-Tronic","valorAtual":321828,"canonicalPath":"/fipe/audi/q5-s-line-black-2-0-tfsi-quat-s-tronic-2024-008270-8/","ano":2024,"marca":"Audi","modelo":"Q5 S-Line Black 2.0 TFSI Quat. S-Tronic","tipo":"carros","displayYear":{"kind":"year","year":2024,"label":"2024","shortLabel":"2024"}},{"vehicleId":"byd-han-ev-eletrico-2024-eletrico","fipeCodigo":"095003-3","displayName":"BYD Han EV (elétrico)","valorAtual":309654,"canonicalPath":"/fipe/byd/han-ev-eletrico-2024-095003-3/","ano":2024,"marca":"BYD","modelo":"Han EV  (Elétrico)","tipo":"carros","displayYear":{"kind":"year","year":2024,"label":"2024","shortLabel":"2024"}}]},"faq":[{"pergunta":"Qual o valor do Lexus Nx-350H 4X4 Dynamic 2.5 16V Aut. (híb.) 2024 na Tabela FIPE?","resposta":"O valor de referência é R$ 317.975 (Jun/26)."},{"pergunta":"Quanto custava o Lexus Nx-350H 4X4 Dynamic 2.5 16V Aut. (híb.) há 6 meses?","resposta":"Há 6 meses o valor era R$ 330.698 — variação de -3,8% no período."},{"pergunta":"O Lexus Nx-350H 4X4 Dynamic 2.5 16V Aut. (híb.) 2024 está valorizando ou desvalorizando?","resposta":"Está desvalorizando +3,8% nos últimos 6 meses."},{"pergunta":"Qual o código FIPE do Lexus Nx-350H 4X4 Dynamic 2.5 16V Aut. (híb.) 2024?","resposta":"O código FIPE é 057054-0, combustível Híbrido."}],"seo":{"title":"Lexus Nx-350H 4X4 Dynamic 2.5 16V Aut. (híb.) 2024 — Tabela FIPE | R$ 317.975","description":"Consulte o preço FIPE do Lexus Nx-350H 4X4 Dynamic 2.5 16V Aut. (híb.) 2024 (código 057054-0): R$ 317.975. Histórico, ficha técnica e veículos relacionados.","h1":"Lexus Nx-350H 4X4 Dynamic 2.5 16V Aut. (híb.) 2024","canonical":"https://pesquisatabelafipe.com.br/fipe/lexus/nx-350h-4x4-dynamic-2-5-16v-aut-hib-2024-057054-0/","canonicalPath":"/fipe/lexus/nx-350h-4x4-dynamic-2-5-16v-aut-hib-2024-057054-0/","og":{"og:type":"article","og:title":"Lexus Nx-350H 4X4 Dynamic 2.5 16V Aut. (híb.) 2024 — Tabela FIPE | R$ 317.975","og:description":"Consulte o preço FIPE do Lexus Nx-350H 4X4 Dynamic 2.5 16V Aut. (híb.) 2024 (código 057054-0): R$ 317.975. Histórico, ficha técnica e veículos relacionados.","og:url":"https://pesquisatabelafipe.com.br/fipe/lexus/nx-350h-4x4-dynamic-2-5-16v-aut-hib-2024-057054-0/","og:site_name":"Pesquisa Tabela FIPE","og:locale":"pt_BR"},"twitter":{"twitter:card":"summary_large_image","twitter:title":"Lexus Nx-350H 4X4 Dynamic 2.5 16V Aut. (híb.) 2024 — Tabela FIPE | R$ 317.975","twitter:description":"Consulte o preço FIPE do Lexus Nx-350H 4X4 Dynamic 2.5 16V Aut. (híb.) 2024 (código 057054-0): R$ 317.975. Histórico, ficha técnica e veículos relacionados."},"jsonLd":[{"@context":"https://schema.org","@type":"Product","name":"Lexus Nx-350H 4X4 Dynamic 2.5 16V Aut. (híb.) 2024","brand":{"@type":"Brand","name":"Lexus"},"sku":"057054-0","url":"https://pesquisatabelafipe.com.br/fipe/lexus/nx-350h-4x4-dynamic-2-5-16v-aut-hib-2024-057054-0/","offers":{"@type":"Offer","priceCurrency":"BRL","price":317975,"availability":"https://schema.org/InStock","url":"https://pesquisatabelafipe.com.br/fipe/lexus/nx-350h-4x4-dynamic-2-5-16v-aut-hib-2024-057054-0/"}},{"@context":"https://schema.org","@type":"BreadcrumbList","itemListElement":[{"@type":"ListItem","position":1,"name":"FIPE","item":"https://pesquisatabelafipe.com.br/fipe/"},{"@type":"ListItem","position":2,"name":"Lexus","item":"https://pesquisatabelafipe.com.br/fipe/lexus/"},{"@type":"ListItem","position":3,"name":"Lexus Nx-350H 4X4 Dynamic 2.5 16V Aut. (híb.) 2024","item":"https://pesquisatabelafipe.com.br/fipe/lexus/nx-350h-4x4-dynamic-2-5-16v-aut-hib-2024-057054-0/"}]},{"@context":"https://schema.org","@type":"FAQPage","mainEntity":[{"@type":"Question","name":"Qual o valor do Lexus Nx-350H 4X4 Dynamic 2.5 16V Aut. (híb.) 2024 na Tabela FIPE?","acceptedAnswer":{"@type":"Answer","text":"O valor de referência é R$ 317.975 (Jun/26)."}},{"@type":"Question","name":"Quanto custava o Lexus Nx-350H 4X4 Dynamic 2.5 16V Aut. (híb.) há 6 meses?","acceptedAnswer":{"@type":"Answer","text":"Há 6 meses o valor era R$ 330.698 — variação de -3,8% no período."}},{"@type":"Question","name":"O Lexus Nx-350H 4X4 Dynamic 2.5 16V Aut. (híb.) 2024 está valorizando ou desvalorizando?","acceptedAnswer":{"@type":"Answer","text":"Está desvalorizando +3,8% nos últimos 6 meses."}},{"@type":"Question","name":"Qual o código FIPE do Lexus Nx-350H 4X4 Dynamic 2.5 16V Aut. (híb.) 2024?","acceptedAnswer":{"@type":"Answer","text":"O código FIPE é 057054-0, combustível Híbrido."}}]}],"breadcrumb":[{"name":"FIPE","path":"/fipe/"},{"name":"Lexus","path":"/fipe/lexus/"},{"name":"Lexus Nx-350H 4X4 Dynamic 2.5 16V Aut. (híb.) 2024","path":"/fipe/lexus/nx-350h-4x4-dynamic-2-5-16v-aut-hib-2024-057054-0/"}]},"sections":{"preco":true,"historico":true,"specs":true,"engine":false,"maintenance":false,"platform":false,"transmission":false,"generation":true,"inmetro":true,"relacionados":true}}