{"geradoEm":"2026-06-23T01:27:54.632Z","bundlePath":"/data/bundles/hyundai/hr-2-5-tci-diesel-rs-rd-2009-015065-7.json","identity":{"vehicleId":"hyundai-hr-2-5-tci-diesel-rs-rd-2009-diesel","marca":"Hyundai","marcaSlug":"hyundai","modelo":"HR 2.5 TCI Diesel (RS/RD)","ano":2009,"anoModelo":2009,"combustivel":"Diesel","tipo":"carros","displayName":"Hyundai HR 2.5 TCI Diesel (RS/RD)","pageSlug":"hr-2-5-tci-diesel-rs-rd-2009-015065-7"},"fipe":{"fipeCodigo":"015065-7","valorAtual":71567,"mesReferencia":"Jun/26","historico":[{"referencia":"Ago/08","valor":47027,"data":"2008-08-01"},{"referencia":"Set/08","valor":47466,"data":"2008-09-01"},{"referencia":"Out/08","valor":47322,"data":"2008-10-01"},{"referencia":"Nov/08","valor":48251,"data":"2008-11-01"},{"referencia":"Dez/08","valor":48290,"data":"2008-12-01"},{"referencia":"Jan/09","valor":48968,"data":"2009-01-01"},{"referencia":"Fev/09","valor":49078,"data":"2009-02-01"},{"referencia":"Mar/09","valor":49015,"data":"2009-03-01"},{"referencia":"Abr/09","valor":48600,"data":"2009-04-01"},{"referencia":"Mai/09","valor":48075,"data":"2009-05-01"},{"referencia":"Jun/09","valor":48308,"data":"2009-06-01"},{"referencia":"Jul/09","valor":46639,"data":"2009-07-01"},{"referencia":"Ago/09","valor":46983,"data":"2009-08-01"},{"referencia":"Set/09","valor":45010,"data":"2009-09-01"},{"referencia":"Out/09","valor":44707,"data":"2009-10-01"},{"referencia":"Nov/09","valor":44803,"data":"2009-11-01"},{"referencia":"Dez/09","valor":44770,"data":"2009-12-01"},{"referencia":"Jan/10","valor":44002,"data":"2010-01-01"},{"referencia":"Fev/10","valor":43970,"data":"2010-02-01"},{"referencia":"Mar/10","valor":44120,"data":"2010-03-01"},{"referencia":"Abr/10","valor":45010,"data":"2010-04-01"},{"referencia":"Mai/10","valor":43507,"data":"2010-05-01"},{"referencia":"Jun/10","valor":44830,"data":"2010-06-01"},{"referencia":"Jul/10","valor":45320,"data":"2010-07-01"},{"referencia":"Ago/10","valor":45465,"data":"2010-08-01"},{"referencia":"Set/10","valor":45502,"data":"2010-09-01"},{"referencia":"Out/10","valor":44900,"data":"2010-10-01"},{"referencia":"Nov/10","valor":45935,"data":"2010-11-01"},{"referencia":"Dez/10","valor":45940,"data":"2010-12-01"},{"referencia":"Jan/11","valor":46165,"data":"2011-01-01"},{"referencia":"Fev/11","valor":46271,"data":"2011-02-01"},{"referencia":"Mar/11","valor":45385,"data":"2011-03-01"},{"referencia":"Abr/11","valor":46602,"data":"2011-04-01"},{"referencia":"Mai/11","valor":47789,"data":"2011-05-01"},{"referencia":"Jun/11","valor":46940,"data":"2011-06-01"},{"referencia":"Jul/11","valor":46420,"data":"2011-07-01"},{"referencia":"Ago/11","valor":46842,"data":"2011-08-01"},{"referencia":"Set/11","valor":46958,"data":"2011-09-01"},{"referencia":"Out/11","valor":46855,"data":"2011-10-01"},{"referencia":"Nov/11","valor":47078,"data":"2011-11-01"},{"referencia":"Dez/11","valor":47594,"data":"2011-12-01"},{"referencia":"Jan/12","valor":48094,"data":"2012-01-01"},{"referencia":"Fev/12","valor":48334,"data":"2012-02-01"},{"referencia":"Mar/12","valor":48458,"data":"2012-03-01"},{"referencia":"Abr/12","valor":48325,"data":"2012-04-01"},{"referencia":"Mai/12","valor":48130,"data":"2012-05-01"},{"referencia":"Jun/12","valor":45573,"data":"2012-06-01"},{"referencia":"Jul/12","valor":45320,"data":"2012-07-01"},{"referencia":"Ago/12","valor":44964,"data":"2012-08-01"},{"referencia":"Set/12","valor":44055,"data":"2012-09-01"},{"referencia":"Out/12","valor":43650,"data":"2012-10-01"},{"referencia":"Nov/12","valor":43179,"data":"2012-11-01"},{"referencia":"Dez/12","valor":43358,"data":"2012-12-01"},{"referencia":"Jan/13","valor":43055,"data":"2013-01-01"},{"referencia":"Fev/13","valor":43125,"data":"2013-02-01"},{"referencia":"Mar/13","valor":43807,"data":"2013-03-01"},{"referencia":"Abr/13","valor":44605,"data":"2013-04-01"},{"referencia":"Mai/13","valor":45369,"data":"2013-05-01"},{"referencia":"Jun/13","valor":45310,"data":"2013-06-01"},{"referencia":"Jul/13","valor":46226,"data":"2013-07-01"},{"referencia":"Ago/13","valor":46057,"data":"2013-08-01"},{"referencia":"Set/13","valor":46399,"data":"2013-09-01"},{"referencia":"Out/13","valor":45689,"data":"2013-10-01"},{"referencia":"Nov/13","valor":45731,"data":"2013-11-01"},{"referencia":"Dez/13","valor":46383,"data":"2013-12-01"},{"referencia":"Jan/14","valor":46738,"data":"2014-01-01"},{"referencia":"Fev/14","valor":46184,"data":"2014-02-01"},{"referencia":"Mar/14","valor":45525,"data":"2014-03-01"},{"referencia":"Abr/14","valor":44978,"data":"2014-04-01"},{"referencia":"Mai/14","valor":44374,"data":"2014-05-01"},{"referencia":"Jun/14","valor":44797,"data":"2014-06-01"},{"referencia":"Jul/14","valor":44125,"data":"2014-07-01"},{"referencia":"Ago/14","valor":43505,"data":"2014-08-01"},{"referencia":"Set/14","valor":42881,"data":"2014-09-01"},{"referencia":"Out/14","valor":42859,"data":"2014-10-01"},{"referencia":"Nov/14","valor":42529,"data":"2014-11-01"},{"referencia":"Dez/14","valor":43011,"data":"2014-12-01"},{"referencia":"Jan/15","valor":42459,"data":"2015-01-01"},{"referencia":"Fev/15","valor":42944,"data":"2015-02-01"},{"referencia":"Mar/15","valor":42426,"data":"2015-03-01"},{"referencia":"Abr/15","valor":42100,"data":"2015-04-01"},{"referencia":"Mai/15","valor":41571,"data":"2015-05-01"},{"referencia":"Jun/15","valor":42076,"data":"2015-06-01"},{"referencia":"Jul/15","valor":41331,"data":"2015-07-01"},{"referencia":"Ago/15","valor":41474,"data":"2015-08-01"},{"referencia":"Set/15","valor":41410,"data":"2015-09-01"},{"referencia":"Out/15","valor":40891,"data":"2015-10-01"},{"referencia":"Nov/15","valor":41307,"data":"2015-11-01"},{"referencia":"Dez/15","valor":42229,"data":"2015-12-01"},{"referencia":"Jan/16","valor":41216,"data":"2016-01-01"},{"referencia":"Fev/16","valor":40253,"data":"2016-02-01"},{"referencia":"Mar/16","valor":41150,"data":"2016-03-01"},{"referencia":"Abr/16","valor":41501,"data":"2016-04-01"},{"referencia":"Mai/16","valor":41686,"data":"2016-05-01"},{"referencia":"Jun/16","valor":40749,"data":"2016-06-01"},{"referencia":"Jul/16","valor":39922,"data":"2016-07-01"},{"referencia":"Ago/16","valor":39880,"data":"2016-08-01"},{"referencia":"Set/16","valor":39836,"data":"2016-09-01"},{"referencia":"Out/16","valor":39968,"data":"2016-10-01"},{"referencia":"Nov/16","valor":39734,"data":"2016-11-01"},{"referencia":"Dez/16","valor":39377,"data":"2016-12-01"},{"referencia":"Jan/17","valor":39167,"data":"2017-01-01"},{"referencia":"Fev/17","valor":39599,"data":"2017-02-01"},{"referencia":"Mar/17","valor":39951,"data":"2017-03-01"},{"referencia":"Abr/17","valor":39495,"data":"2017-04-01"},{"referencia":"Mai/17","valor":38540,"data":"2017-05-01"},{"referencia":"Jun/17","valor":38634,"data":"2017-06-01"},{"referencia":"Jul/17","valor":38536,"data":"2017-07-01"},{"referencia":"Ago/17","valor":39041,"data":"2017-08-01"},{"referencia":"Set/17","valor":39581,"data":"2017-09-01"},{"referencia":"Out/17","valor":39726,"data":"2017-10-01"},{"referencia":"Nov/17","valor":40281,"data":"2017-11-01"},{"referencia":"Dez/17","valor":40704,"data":"2017-12-01"},{"referencia":"Jan/18","valor":41235,"data":"2018-01-01"},{"referencia":"Fev/18","valor":41779,"data":"2018-02-01"},{"referencia":"Mar/18","valor":41982,"data":"2018-03-01"},{"referencia":"Abr/18","valor":42535,"data":"2018-04-01"},{"referencia":"Mai/18","valor":41986,"data":"2018-05-01"},{"referencia":"Jun/18","valor":42215,"data":"2018-06-01"},{"referencia":"Jul/18","valor":42360,"data":"2018-07-01"},{"referencia":"Ago/18","valor":42483,"data":"2018-08-01"},{"referencia":"Set/18","valor":41966,"data":"2018-09-01"},{"referencia":"Out/18","valor":41709,"data":"2018-10-01"},{"referencia":"Nov/18","valor":42257,"data":"2018-11-01"},{"referencia":"Dez/18","valor":42354,"data":"2018-12-01"},{"referencia":"Jan/19","valor":41851,"data":"2019-01-01"},{"referencia":"Fev/19","valor":42141,"data":"2019-02-01"},{"referencia":"Mar/19","valor":42031,"data":"2019-03-01"},{"referencia":"Abr/19","valor":42302,"data":"2019-04-01"},{"referencia":"Mai/19","valor":42010,"data":"2019-05-01"},{"referencia":"Jun/19","valor":42182,"data":"2019-06-01"},{"referencia":"Jul/19","valor":41958,"data":"2019-07-01"},{"referencia":"Ago/19","valor":41904,"data":"2019-08-01"},{"referencia":"Set/19","valor":41879,"data":"2019-09-01"},{"referencia":"Out/19","valor":41719,"data":"2019-10-01"},{"referencia":"Nov/19","valor":41584,"data":"2019-11-01"},{"referencia":"Dez/19","valor":41444,"data":"2019-12-01"},{"referencia":"Jan/20","valor":41032,"data":"2020-01-01"},{"referencia":"Fev/20","valor":40926,"data":"2020-02-01"},{"referencia":"Mar/20","valor":40723,"data":"2020-03-01"},{"referencia":"Abr/20","valor":40587,"data":"2020-04-01"},{"referencia":"Mai/20","valor":40580,"data":"2020-05-01"},{"referencia":"Jun/20","valor":40505,"data":"2020-06-01"},{"referencia":"Jul/20","valor":40460,"data":"2020-07-01"},{"referencia":"Ago/20","valor":40506,"data":"2020-08-01"},{"referencia":"Set/20","valor":40414,"data":"2020-09-01"},{"referencia":"Out/20","valor":40686,"data":"2020-10-01"},{"referencia":"Nov/20","valor":40912,"data":"2020-11-01"},{"referencia":"Dez/20","valor":42202,"data":"2020-12-01"},{"referencia":"Jan/21","valor":43419,"data":"2021-01-01"},{"referencia":"Fev/21","valor":43507,"data":"2021-02-01"},{"referencia":"Mar/21","valor":44887,"data":"2021-03-01"},{"referencia":"Abr/21","valor":46520,"data":"2021-04-01"},{"referencia":"Mai/21","valor":48409,"data":"2021-05-01"},{"referencia":"Jun/21","valor":50649,"data":"2021-06-01"},{"referencia":"Jul/21","valor":52907,"data":"2021-07-01"},{"referencia":"Ago/21","valor":54564,"data":"2021-08-01"},{"referencia":"Set/21","valor":56582,"data":"2021-09-01"},{"referencia":"Out/21","valor":57657,"data":"2021-10-01"},{"referencia":"Nov/21","valor":58644,"data":"2021-11-01"},{"referencia":"Dez/21","valor":59768,"data":"2021-12-01"},{"referencia":"Jan/22","valor":62696,"data":"2022-01-01"},{"referencia":"Fev/22","valor":64799,"data":"2022-02-01"},{"referencia":"Mar/22","valor":65158,"data":"2022-03-01"},{"referencia":"Abr/22","valor":63194,"data":"2022-04-01"},{"referencia":"Mai/22","valor":65741,"data":"2022-05-01"},{"referencia":"Jun/22","valor":65819,"data":"2022-06-01"},{"referencia":"Jul/22","valor":64818,"data":"2022-07-01"},{"referencia":"Ago/22","valor":65834,"data":"2022-08-01"},{"referencia":"Set/22","valor":65214,"data":"2022-09-01"},{"referencia":"Out/22","valor":66541,"data":"2022-10-01"},{"referencia":"Nov/22","valor":68869,"data":"2022-11-01"},{"referencia":"Dez/22","valor":68354,"data":"2022-12-01"},{"referencia":"Jan/23","valor":68279,"data":"2023-01-01"},{"referencia":"Fev/23","valor":68399,"data":"2023-02-01"},{"referencia":"Mar/23","valor":66609,"data":"2023-03-01"},{"referencia":"Abr/23","valor":65959,"data":"2023-04-01"},{"referencia":"Mai/23","valor":66076,"data":"2023-05-01"},{"referencia":"Jun/23","valor":65077,"data":"2023-06-01"},{"referencia":"Jul/23","valor":66709,"data":"2023-07-01"},{"referencia":"Ago/23","valor":68229,"data":"2023-08-01"},{"referencia":"Set/23","valor":69322,"data":"2023-09-01"},{"referencia":"Out/23","valor":68648,"data":"2023-10-01"},{"referencia":"Nov/23","valor":69210,"data":"2023-11-01"},{"referencia":"Dez/23","valor":70512,"data":"2023-12-01"},{"referencia":"Jan/24","valor":69353,"data":"2024-01-01"},{"referencia":"Fev/24","valor":69162,"data":"2024-02-01"},{"referencia":"Mar/24","valor":69410,"data":"2024-03-01"},{"referencia":"Abr/24","valor":70967,"data":"2024-04-01"},{"referencia":"Mai/24","valor":68936,"data":"2024-05-01"},{"referencia":"Jun/24","valor":68551,"data":"2024-06-01"},{"referencia":"Jul/24","valor":69888,"data":"2024-07-01"},{"referencia":"Ago/24","valor":69214,"data":"2024-08-01"},{"referencia":"Set/24","valor":70710,"data":"2024-09-01"},{"referencia":"Out/24","valor":70206,"data":"2024-10-01"},{"referencia":"Nov/24","valor":69769,"data":"2024-11-01"},{"referencia":"Dez/24","valor":69931,"data":"2024-12-01"},{"referencia":"Jan/25","valor":71274,"data":"2025-01-01"},{"referencia":"Fev/25","valor":70508,"data":"2025-02-01"},{"referencia":"Mar/25","valor":69783,"data":"2025-03-01"},{"referencia":"Abr/25","valor":69967,"data":"2025-04-01"},{"referencia":"Mai/25","valor":70763,"data":"2025-05-01"},{"referencia":"Jun/25","valor":72736,"data":"2025-06-01"},{"referencia":"Jul/25","valor":71569,"data":"2025-07-01"},{"referencia":"Ago/25","valor":70464,"data":"2025-08-01"},{"referencia":"Set/25","valor":71168,"data":"2025-09-01"},{"referencia":"Out/25","valor":70487,"data":"2025-10-01"},{"referencia":"Nov/25","valor":71682,"data":"2025-11-01"},{"referencia":"Dez/25","valor":72546,"data":"2025-12-01"},{"referencia":"Jan/26","valor":72913,"data":"2026-01-01"},{"referencia":"Fev/26","valor":73905,"data":"2026-02-01"},{"referencia":"Mar/26","valor":71972,"data":"2026-03-01"},{"referencia":"Abr/26","valor":72601,"data":"2026-04-01"},{"referencia":"Mai/26","valor":72780,"data":"2026-05-01"},{"referencia":"Jun/26","valor":71567,"data":"2026-06-01"}],"trend6m":-1.3494886003363384},"specs":null,"engine":null,"maintenance":null,"platform":null,"transmission":null,"generation":{"geracaoId":"hr-2","familia":"hyundai|hr","catalogEntry":{"id":"hr-2","numero":2,"anoInicio":2005,"anoFim":2022,"label":"HR gen 2 (2005-2022)"}},"inmetro":{"consumoCidade":10.2,"consumoEstrada":8.9,"consumoCidadeEtanol":null,"consumoEstradaEtanol":null,"potenciaCv":null,"cilindradaCc":null,"classificacaoEnergetica":"B","fonte":"inmetro-pbev"},"safety":null,"recalls":null,"warranty":{"garantiaTotalAnos":5,"garantiaAnticorrosaoAnos":7,"garantiaMotorAnos":5,"fonte":"hyundai.com.br/garantia"},"related":{"mesmaGeracao":[{"vehicleId":"hyundai-hr-2-5-tci-diesel-rs-rd-2005-diesel","fipeCodigo":"015065-7","displayName":"Hyundai HR 2.5 TCI Diesel (RS/RD)","valorAtual":53077,"canonicalPath":"/fipe/hyundai/hr-2-5-tci-diesel-rs-rd-2005-015065-7/","ano":2005,"marca":"Hyundai"},{"vehicleId":"hyundai-hr-2-5-tci-diesel-rs-rd-2006-diesel","fipeCodigo":"015065-7","displayName":"Hyundai HR 2.5 TCI Diesel (RS/RD)","valorAtual":54404,"canonicalPath":"/fipe/hyundai/hr-2-5-tci-diesel-rs-rd-2006-015065-7/","ano":2006,"marca":"Hyundai"},{"vehicleId":"hyundai-hr-2-5-tci-diesel-rs-rd-2007-diesel","fipeCodigo":"015065-7","displayName":"Hyundai HR 2.5 TCI Diesel (RS/RD)","valorAtual":67446,"canonicalPath":"/fipe/hyundai/hr-2-5-tci-diesel-rs-rd-2007-015065-7/","ano":2007,"marca":"Hyundai"},{"vehicleId":"hyundai-hr-2-5-tci-diesel-rs-rd-2008-diesel","fipeCodigo":"015065-7","displayName":"Hyundai HR 2.5 TCI Diesel (RS/RD)","valorAtual":69133,"canonicalPath":"/fipe/hyundai/hr-2-5-tci-diesel-rs-rd-2008-015065-7/","ano":2008,"marca":"Hyundai"},{"vehicleId":"hyundai-hr-2-5-tci-diesel-rs-rd-2010-diesel","fipeCodigo":"015065-7","displayName":"Hyundai HR 2.5 TCI Diesel (RS/RD)","valorAtual":73357,"canonicalPath":"/fipe/hyundai/hr-2-5-tci-diesel-rs-rd-2010-015065-7/","ano":2010,"marca":"Hyundai"},{"vehicleId":"hyundai-hr-2-5-tci-diesel-rs-rd-2011-diesel","fipeCodigo":"015065-7","displayName":"Hyundai HR 2.5 TCI Diesel (RS/RD)","valorAtual":80993,"canonicalPath":"/fipe/hyundai/hr-2-5-tci-diesel-rs-rd-2011-015065-7/","ano":2011,"marca":"Hyundai"}],"mesmaFamilia":[{"vehicleId":"hyundai-hr-2-5-4wd-diesel-2024-diesel","fipeCodigo":"015229-3","displayName":"Hyundai HR 2.5 4WD Diesel","valorAtual":162154,"canonicalPath":"/fipe/hyundai/hr-2-5-4wd-diesel-2024-015229-3/","ano":2024,"marca":"Hyundai"},{"vehicleId":"hyundai-hr-2-5-4wd-diesel-2025-diesel","fipeCodigo":"015229-3","displayName":"Hyundai HR 2.5 4WD Diesel","valorAtual":166483,"canonicalPath":"/fipe/hyundai/hr-2-5-4wd-diesel-2025-015229-3/","ano":2025,"marca":"Hyundai"},{"vehicleId":"hyundai-hr-2-5-4wd-diesel-0-diesel","fipeCodigo":"015229-3","displayName":"Hyundai HR 2.5 4WD Diesel  (null)","valorAtual":182537,"canonicalPath":"/fipe/hyundai/hr-2-5-4wd-diesel-0-015229-3/","ano":0,"marca":"Hyundai"},{"vehicleId":"hyundai-hr-2-5-tci-diesel-rs-rd-2005-diesel","fipeCodigo":"015065-7","displayName":"Hyundai HR 2.5 TCI Diesel (RS/RD)","valorAtual":53077,"canonicalPath":"/fipe/hyundai/hr-2-5-tci-diesel-rs-rd-2005-015065-7/","ano":2005,"marca":"Hyundai"},{"vehicleId":"hyundai-hr-2-5-tci-diesel-rs-rd-2006-diesel","fipeCodigo":"015065-7","displayName":"Hyundai HR 2.5 TCI Diesel (RS/RD)","valorAtual":54404,"canonicalPath":"/fipe/hyundai/hr-2-5-tci-diesel-rs-rd-2006-015065-7/","ano":2006,"marca":"Hyundai"},{"vehicleId":"hyundai-hr-2-5-tci-diesel-rs-rd-2007-diesel","fipeCodigo":"015065-7","displayName":"Hyundai HR 2.5 TCI Diesel (RS/RD)","valorAtual":67446,"canonicalPath":"/fipe/hyundai/hr-2-5-tci-diesel-rs-rd-2007-015065-7/","ano":2007,"marca":"Hyundai"}],"mesmaPlataforma":[],"mesmoMotor":[],"mesmaTransmissao":[],"mesmaFaixaPreco":[{"vehicleId":"agrale-marrua-am-100-2-8-cs-tdi-diesel-2010-diesel","fipeCodigo":"060003-2","displayName":"Agrale MARRUÁ AM 100 2.8  CS TDI Diesel","valorAtual":63131,"canonicalPath":"/fipe/agrale/marrua-am-100-2-8-cs-tdi-diesel-2010-060003-2/","ano":2010,"marca":"Agrale"},{"vehicleId":"agrale-marrua-am-100-2-8-cs-tdi-diesel-2011-diesel","fipeCodigo":"060003-2","displayName":"Agrale MARRUÁ AM 100 2.8  CS TDI Diesel","valorAtual":75227,"canonicalPath":"/fipe/agrale/marrua-am-100-2-8-cs-tdi-diesel-2011-060003-2/","ano":2011,"marca":"Agrale"},{"vehicleId":"agrale-marrua-am-100-2-8-cs-tdi-diesel-2012-diesel","fipeCodigo":"060003-2","displayName":"Agrale MARRUÁ AM 100 2.8  CS TDI Diesel","valorAtual":90210,"canonicalPath":"/fipe/agrale/marrua-am-100-2-8-cs-tdi-diesel-2012-060003-2/","ano":2012,"marca":"Agrale"},{"vehicleId":"agrale-marrua-am-100-2-8-cs-tdi-diesel-2013-diesel","fipeCodigo":"060003-2","displayName":"Agrale MARRUÁ AM 100 2.8  CS TDI Diesel","valorAtual":98450,"canonicalPath":"/fipe/agrale/marrua-am-100-2-8-cs-tdi-diesel-2013-060003-2/","ano":2013,"marca":"Agrale"},{"vehicleId":"agrale-marrua-am-100-2-8-cd-tdi-diesel-2010-diesel","fipeCodigo":"060004-0","displayName":"Agrale MARRUÁ AM 100 2.8 CD TDI Diesel","valorAtual":66128,"canonicalPath":"/fipe/agrale/marrua-am-100-2-8-cd-tdi-diesel-2010-060004-0/","ano":2010,"marca":"Agrale"},{"vehicleId":"agrale-marrua-am-100-2-8-cd-tdi-diesel-2011-diesel","fipeCodigo":"060004-0","displayName":"Agrale MARRUÁ AM 100 2.8 CD TDI Diesel","valorAtual":77186,"canonicalPath":"/fipe/agrale/marrua-am-100-2-8-cd-tdi-diesel-2011-060004-0/","ano":2011,"marca":"Agrale"}],"concorrentes":[{"vehicleId":"agrale-marrua-am-100-2-8-cs-tdi-diesel-2010-diesel","fipeCodigo":"060003-2","displayName":"Agrale MARRUÁ AM 100 2.8  CS TDI Diesel","valorAtual":63131,"canonicalPath":"/fipe/agrale/marrua-am-100-2-8-cs-tdi-diesel-2010-060003-2/","ano":2010,"marca":"Agrale"},{"vehicleId":"agrale-marrua-am-100-2-8-cs-tdi-diesel-2011-diesel","fipeCodigo":"060003-2","displayName":"Agrale MARRUÁ AM 100 2.8  CS TDI Diesel","valorAtual":75227,"canonicalPath":"/fipe/agrale/marrua-am-100-2-8-cs-tdi-diesel-2011-060003-2/","ano":2011,"marca":"Agrale"},{"vehicleId":"agrale-marrua-am-100-2-8-cs-tdi-diesel-2012-diesel","fipeCodigo":"060003-2","displayName":"Agrale MARRUÁ AM 100 2.8  CS TDI Diesel","valorAtual":90210,"canonicalPath":"/fipe/agrale/marrua-am-100-2-8-cs-tdi-diesel-2012-060003-2/","ano":2012,"marca":"Agrale"},{"vehicleId":"agrale-marrua-am-100-2-8-cs-tdi-diesel-2013-diesel","fipeCodigo":"060003-2","displayName":"Agrale MARRUÁ AM 100 2.8  CS TDI Diesel","valorAtual":98450,"canonicalPath":"/fipe/agrale/marrua-am-100-2-8-cs-tdi-diesel-2013-060003-2/","ano":2013,"marca":"Agrale"},{"vehicleId":"agrale-marrua-am-100-2-8-cd-tdi-diesel-2010-diesel","fipeCodigo":"060004-0","displayName":"Agrale MARRUÁ AM 100 2.8 CD TDI Diesel","valorAtual":66128,"canonicalPath":"/fipe/agrale/marrua-am-100-2-8-cd-tdi-diesel-2010-060004-0/","ano":2010,"marca":"Agrale"},{"vehicleId":"agrale-marrua-am-100-2-8-cd-tdi-diesel-2011-diesel","fipeCodigo":"060004-0","displayName":"Agrale MARRUÁ AM 100 2.8 CD TDI Diesel","valorAtual":77186,"canonicalPath":"/fipe/agrale/marrua-am-100-2-8-cd-tdi-diesel-2011-060004-0/","ano":2011,"marca":"Agrale"}]},"faq":[{"pergunta":"Qual o valor do Hyundai HR 2.5 TCI Diesel (RS/RD) 2009 na Tabela FIPE?","resposta":"O valor de referência é R$ 71.567 (Jun/26)."},{"pergunta":"Quanto custava o Hyundai HR 2.5 TCI Diesel (RS/RD) há 6 meses?","resposta":"Há 6 meses o valor era R$ 72.546 — variação de -1,3% no período."},{"pergunta":"O Hyundai HR 2.5 TCI Diesel (RS/RD) 2009 está valorizando ou desvalorizando?","resposta":"Está desvalorizando +1,3% nos últimos 6 meses."},{"pergunta":"Qual o código FIPE do Hyundai HR 2.5 TCI Diesel (RS/RD) 2009?","resposta":"O código FIPE é 015065-7, combustível Diesel."}],"seo":{"title":"Hyundai HR 2.5 TCI Diesel (RS/RD) 2009 — Tabela FIPE | R$ 71.567","description":"Consulte o preço FIPE do Hyundai HR 2.5 TCI Diesel (RS/RD) 2009 (código 015065-7): R$ 71.567. Histórico, ficha técnica e veículos relacionados.","h1":"Hyundai HR 2.5 TCI Diesel (RS/RD) 2009","canonical":"https://pesquisatabelafipe.com.br/fipe/hyundai/hr-2-5-tci-diesel-rs-rd-2009-015065-7/","canonicalPath":"/fipe/hyundai/hr-2-5-tci-diesel-rs-rd-2009-015065-7/","og":{"og:type":"article","og:title":"Hyundai HR 2.5 TCI Diesel (RS/RD) 2009 — Tabela FIPE | R$ 71.567","og:description":"Consulte o preço FIPE do Hyundai HR 2.5 TCI Diesel (RS/RD) 2009 (código 015065-7): R$ 71.567. Histórico, ficha técnica e veículos relacionados.","og:url":"https://pesquisatabelafipe.com.br/fipe/hyundai/hr-2-5-tci-diesel-rs-rd-2009-015065-7/","og:site_name":"Pesquisa Tabela FIPE","og:locale":"pt_BR"},"twitter":{"twitter:card":"summary_large_image","twitter:title":"Hyundai HR 2.5 TCI Diesel (RS/RD) 2009 — Tabela FIPE | R$ 71.567","twitter:description":"Consulte o preço FIPE do Hyundai HR 2.5 TCI Diesel (RS/RD) 2009 (código 015065-7): R$ 71.567. Histórico, ficha técnica e veículos relacionados."},"jsonLd":[{"@context":"https://schema.org","@type":"Product","name":"Hyundai HR 2.5 TCI Diesel (RS/RD) 2009","brand":{"@type":"Brand","name":"Hyundai"},"sku":"015065-7","url":"https://pesquisatabelafipe.com.br/fipe/hyundai/hr-2-5-tci-diesel-rs-rd-2009-015065-7/","offers":{"@type":"Offer","priceCurrency":"BRL","price":71567,"availability":"https://schema.org/InStock","url":"https://pesquisatabelafipe.com.br/fipe/hyundai/hr-2-5-tci-diesel-rs-rd-2009-015065-7/"}},{"@context":"https://schema.org","@type":"BreadcrumbList","itemListElement":[{"@type":"ListItem","position":1,"name":"FIPE","item":"https://pesquisatabelafipe.com.br/fipe/"},{"@type":"ListItem","position":2,"name":"Hyundai","item":"https://pesquisatabelafipe.com.br/fipe/hyundai/"},{"@type":"ListItem","position":3,"name":"Hyundai HR 2.5 TCI Diesel (RS/RD) 2009","item":"https://pesquisatabelafipe.com.br/fipe/hyundai/hr-2-5-tci-diesel-rs-rd-2009-015065-7/"}]},{"@context":"https://schema.org","@type":"FAQPage","mainEntity":[{"@type":"Question","name":"Qual o valor do Hyundai HR 2.5 TCI Diesel (RS/RD) 2009 na Tabela FIPE?","acceptedAnswer":{"@type":"Answer","text":"O valor de referência é R$ 71.567 (Jun/26)."}},{"@type":"Question","name":"Quanto custava o Hyundai HR 2.5 TCI Diesel (RS/RD) há 6 meses?","acceptedAnswer":{"@type":"Answer","text":"Há 6 meses o valor era R$ 72.546 — variação de -1,3% no período."}},{"@type":"Question","name":"O Hyundai HR 2.5 TCI Diesel (RS/RD) 2009 está valorizando ou desvalorizando?","acceptedAnswer":{"@type":"Answer","text":"Está desvalorizando +1,3% nos últimos 6 meses."}},{"@type":"Question","name":"Qual o código FIPE do Hyundai HR 2.5 TCI Diesel (RS/RD) 2009?","acceptedAnswer":{"@type":"Answer","text":"O código FIPE é 015065-7, combustível Diesel."}}]}],"breadcrumb":[{"name":"FIPE","path":"/fipe/"},{"name":"Hyundai","path":"/fipe/hyundai/"},{"name":"Hyundai HR 2.5 TCI Diesel (RS/RD) 2009","path":"/fipe/hyundai/hr-2-5-tci-diesel-rs-rd-2009-015065-7/"}]},"sections":{"preco":true,"historico":true,"specs":false,"engine":false,"maintenance":false,"platform":false,"transmission":false,"generation":true,"inmetro":true,"relacionados":true}}